{"datiDettRef":[


 {"DscProd": "PERMIXONOS 16CPS 320MG","DscDitta": "PIERRE FABRE PHARMA Srl","FFt": 1,"FPz": 2,"FFatt": 10836.8,"FFatt_D": -2.07,"FPezzi": 521,"FPezzi_D": -2.07,"FQuota": 6.52,"FPrezzo": 20.8,"CFt": 4,"CPz": 2,"CFatt": 4276.9,"CFatt_D": 8.12,"CPezzi": 207,"CPezzi_D": 6.31,"CQuota": 4.24,"CPrezzo": 20.71},
{"DscProd": "OMNIC20CPS 0,4MG RM","DscDitta": "ASTELLAS PHARMA SpA","FFt": 2,"FPz": 3,"FFatt": 8393.7,"FFatt_D": 10.66,"FPezzi": 1142,"FPezzi_D": 10.66,"FQuota": 14.28,"FPrezzo": 7.35,"CFt": 2,"CPz": 4,"CFatt": 5486.56,"CFatt_D": 14.62,"CPezzi": 747,"CPezzi_D": 13.9,"CQuota": 15.32,"CPrezzo": 7.35},
{"DscProd": "XATRAL30CPR 10MG RP","DscDitta": "SANOFI SpA","FFt": 3,"FPz": 4,"FFatt": 8368.1,"FFatt_D": -5.31,"FPezzi": 785,"FPezzi_D": -5.31,"FQuota": 9.82,"FPrezzo": 10.66,"CFt": 6,"CPz": 3,"CFatt": 3390.88,"CFatt_D": 12.75,"CPezzi": 318,"CPezzi_D": 11.33,"CQuota": 6.53,"CPrezzo": 10.65},
{"DscProd": "AVODART30CPS MOLLI 0,5MG","DscDitta": "GLAXOSMITHKLINE SpA","FFt": 4,"FPz": 1,"FFatt": 8304.9,"FFatt_D": 4.14,"FPezzi": 705,"FPezzi_D": 4.14,"FQuota": 8.82,"FPrezzo": 11.78,"CFt": 1,"CPz": 15,"CFatt": 5586.52,"CFatt_D": -32.52,"CPezzi": 474,"CPezzi_D": -6.83,"CQuota": 9.73,"CPrezzo": 11.77},
{"DscProd": "PROFLUSS 15CPS","DscDitta": "KONPHARMA Srl","FFt": 5,"FPz": 15,"FFatt": 6055.16,"FFatt_D": 18.81,"FPezzi": 322,"FPezzi_D": 18.38,"FQuota": 4.03,"FPrezzo": 18.8,"CFt": 3,"CPz": 6,"CFatt": 1681.49,"CFatt_D": 27.05,"CPezzi": 84,"CPezzi_D": 25.22,"CQuota": 1.73,"CPrezzo": 19.92},
{"DscProd": "UROREC30CPS 8MG","DscDitta": "RECORDATI SpA","FFt": 6,"FPz": 6,"FFatt": 5082,"FFatt_D": 21.32,"FPezzi": 330,"FPezzi_D": 21.32,"FQuota": 4.13,"FPrezzo": 15.4,"CFt": 11,"CPz": 1,"CFatt": 4596,"CFatt_D": 13.24,"CPezzi": 299,"CPezzi_D": 13,"CQuota": 6.12,"CPrezzo": 15.39},
{"DscProd": "LFP PROSTACOMPLEX 30CPS","DscDitta": "UNIFARCO SpA","FFt": 7,"FPz": 5,"FFatt": 4346.5,"FFatt_D": -7.32,"FPezzi": 278,"FPezzi_D": -14.98,"FQuota": 3.48,"FPrezzo": 15.63,"CFt": 5,"CPz": 59,"CFatt": 262.34,"CFatt_D": 7.3,"CPezzi": 16,"CPezzi_D": -4,"CQuota": 0.34,"CPrezzo": 15.94},
{"DscProd": "ADENOMIX ALFA 30CPR","DscDitta": "BIO STILOGIT PHARMACEUTIC. Srl","FFt": 8,"FPz": 10,"FFatt": 3684.06,"FFatt_D": -3.51,"FPezzi": 198,"FPezzi_D": -3.41,"FQuota": 2.48,"FPrezzo": 18.61,"CFt": 15,"CPz": 11,"CFatt": 373.8,"CFatt_D": 5.4,"CPezzi": 19,"CPezzi_D": 3.4,"CQuota": 0.4,"CPrezzo": 19.28},
{"DscProd": "IDIPROST 15CPS","DscDitta": "IDI INTEGRATORI DIETET.IT. Srl","FFt": 9,"FPz": 7,"FFatt": 2961.9,"FFatt_D": 100.49,"FPezzi": 179,"FPezzi_D": 101.12,"FQuota": 2.24,"FPrezzo": 16.55,"CFt": 13,"CPz": 123,"CFatt": 336.33,"CFatt_D": 26.06,"CPezzi": 20,"CPezzi_D": 25.98,"CQuota": 0.41,"CPrezzo": 17},
{"DscProd": "ALFUZOSINA MY30CPR 10MG RP","DscDitta": "MYLAN SpA","FFt": 10,"FPz": 14,"FFatt": 2783.26,"FFatt_D": 38.43,"FPezzi": 317,"FPezzi_D": 38.43,"FQuota": 3.96,"FPrezzo": 8.78,"CFt": 19,"CPz": 81,"CFatt": 624.33,"CFatt_D": 15.68,"CPezzi": 71,"CPezzi_D": 13.75,"CQuota": 1.46,"CPrezzo": 8.77},
{"DscProd": "SILODYX30CPS 8MG","DscDitta": "TAKEDA ITALIA SpA","FFt": 11,"FPz": 8,"FFatt": 2356.2,"FFatt_D": -17.3,"FPezzi": 153,"FPezzi_D": -17.3,"FQuota": 1.91,"FPrezzo": 15.4,"CFt": 26,"CPz": 5,"CFatt": 1777.15,"CFatt_D": 6.71,"CPezzi": 115,"CPezzi_D": 5.62,"CQuota": 2.37,"CPrezzo": 15.39},
{"DscProd": "PROSTENIL ADVANCED 60OPR","DscDitta": "ABOCA SpA SOCIETA' AGRICOLA","FFt": 12,"FPz": 9,"FFatt": 2195.7,"FFatt_D": 206.49,"FPezzi": 99,"FPezzi_D": 209.38,"FQuota": 1.24,"FPrezzo": 22.18,"CFt": 29,"CPz": 39,"CFatt": 816.66,"CFatt_D": 87.95,"CPezzi": 33,"CPezzi_D": 87.23,"CQuota": 0.69,"CPrezzo": 24.39},
{"DscProd": "PROSTAMOL 30CPS MOLLI","DscDitta": "A.MENARINI IND.FARM.RIUN.Srl","FFt": 13,"FPz": 11,"FFatt": 2116.72,"FFatt_D": -14.82,"FPezzi": 115,"FPezzi_D": -21.23,"FQuota": 1.44,"FPrezzo": 18.41,"CFt": 12,"CPz": 121,"CFatt": 1300.64,"CFatt_D": -26.12,"CPezzi": 60,"CPezzi_D": -34.22,"CQuota": 1.23,"CPrezzo": 21.65},
{"DscProd": "FINASTERIDE TEVA15CPR RIV 5MG","DscDitta": "TEVA ITALIA Srl","FFt": 14,"FPz": 21,"FFatt": 1923.04,"FFatt_D": 31.49,"FPezzi": 238,"FPezzi_D": 31.49,"FQuota": 2.98,"FPrezzo": 8.08,"CFt": 81,"CPz": 19,"CFatt": 555.76,"CFatt_D": 13.05,"CPezzi": 69,"CPezzi_D": 11.97,"CQuota": 1.41,"CPrezzo": 8.07},
{"DscProd": "TAMSULOSIN MY20CPS 0,4MG RM","DscDitta": "MYLAN SpA","FFt": 15,"FPz": 19,"FFatt": 1891.89,"FFatt_D": 42.05,"FPezzi": 429,"FPezzi_D": 42.05,"FQuota": 5.37,"FPrezzo": 4.41,"CFt": 59,"CPz": 38,"CFatt": 1369.82,"CFatt_D": 21.12,"CPezzi": 311,"CPezzi_D": 20.76,"CQuota": 6.38,"CPrezzo": 4.41},
{"DscProd": "IDIPROST GOLD 15CPS","DscDitta": "IDI INTEGRATORI DIETET.IT. Srl","FFt": 16,"FPz": 13,"FFatt": 1645.92,"FFatt_D": 0.33,"FPezzi": 85,"FPezzi_D": 0,"FQuota": 1.06,"FPrezzo": 19.36,"CFt": 10,"CPz": 10,"CFatt": 416.94,"CFatt_D": 7.36,"CPezzi": 20,"CPezzi_D": 3.45,"CQuota": 0.42,"CPrezzo": 20.37},
{"DscProd": "PROSTAMOL 60CPR","DscDitta": "A.MENARINI IND.FARM.RIUN.Srl","FFt": 17,"FPz": 12,"FFatt": 1614.3,"FFatt_D": null,"FPezzi": 47,"FPezzi_D": null,"FQuota": 0.59,"FPrezzo": 34.35,"CFt": 21,"CPz": 14,"CFatt": 466.76,"CFatt_D": null,"CPezzi": 14,"CPezzi_D": null,"CQuota": 0.29,"CPrezzo": 33.52},
{"DscProd": "DEPROX 500 30CPR","DscDitta": "IDI INTEGRATORI DIETET.IT. Srl","FFt": 18,"FPz": 39,"FFatt": 1556.45,"FFatt_D": 68.26,"FPezzi": 62,"FPezzi_D": 67.57,"FQuota": 0.78,"FPrezzo": 25.1,"CFt": 35,"CPz": 26,"CFatt": 472.16,"CFatt_D": 8.82,"CPezzi": 18,"CPezzi_D": 11.33,"CQuota": 0.36,"CPrezzo": 26.79},
{"DscProd": "MITTOVAL30CPR 10MG RP","DscDitta": "SANOFI SpA","FFt": 19,"FPz": 40,"FFatt": 1480.82,"FFatt_D": -19.62,"FPezzi": 127,"FPezzi_D": -19.62,"FQuota": 1.59,"FPrezzo": 11.66,"CFt": 14,"CPz": 52,"CFatt": 933.18,"CFatt_D": 10.56,"CPezzi": 80,"CPezzi_D": 9.52,"CQuota": 1.64,"CPrezzo": 11.65},
{"DscProd": "VESOMNI30CPR 6MG+0,4MG RM","DscDitta": "ASTELLAS PHARMA SpA","FFt": 20,"FPz": 28,"FFatt": 1456,"FFatt_D": 12,"FPezzi": 28,"FPezzi_D": 12,"FQuota": 0.35,"FPrezzo": 52,"CFt": 32,"CPz": 21,"CFatt": 424.62,"CFatt_D": 21.83,"CPezzi": 8,"CPezzi_D": 15.66,"CQuota": 0.17,"CPrezzo": 51.34},
{"DscProd": "FINASTID15CPR RIV 5MG","DscDitta": "NEOPHARMED GENTILI Srl","FFt": 21,"FPz": 44,"FFatt": 1360,"FFatt_D": 0,"FPezzi": 136,"FPezzi_D": 0,"FQuota": 1.7,"FPrezzo": 10,"CFt": 38,"CPz": 13,"CFatt": 612.1,"CFatt_D": 8.21,"CPezzi": 61,"CPezzi_D": 6.78,"CQuota": 1.26,"CPrezzo": 9.99},
{"DscProd": "PURYPROST 15CPS","DscDitta": "PURYTRA FARMACEUTICI SpA","FFt": 22,"FPz": 16,"FFatt": 1221.3,"FFatt_D": -41.65,"FPezzi": 59,"FPezzi_D": -41.58,"FQuota": 0.74,"FPrezzo": 20.7,"CFt": 52,"CPz": 40,"CFatt": 199.63,"CFatt_D": -12.68,"CPezzi": 9,"CPezzi_D": -15.63,"CQuota": 0.19,"CPrezzo": 21.81},
{"DscProd": "FORPROST 400 15CPS MOLLI","DscDitta": "SHEDIR PHARMA Srl Unipersonale","FFt": 23,"FPz": 32,"FFatt": 1177.05,"FFatt_D": 17.15,"FPezzi": 61,"FPezzi_D": 19.61,"FQuota": 0.76,"FPrezzo": 19.3,"CFt": 18,"CPz": 32,"CFatt": 409.44,"CFatt_D": -20.81,"CPezzi": 20,"CPezzi_D": -18.09,"CQuota": 0.41,"CPrezzo": 20.62},
{"DscProd": "PROXIZAL 300 30CPS","DscDitta": "VALDERMA Srl","FFt": 24,"FPz": 26,"FFatt": 1128.5,"FFatt_D": -37.62,"FPezzi": 50,"FPezzi_D": -36.71,"FQuota": 0.63,"FPrezzo": 22.57,"CFt": 17,"CPz": 35,"CFatt": 109.44,"CFatt_D": -23.29,"CPezzi": 5,"CPezzi_D": -17.81,"CQuota": 0.1,"CPrezzo": 23.62},
{"DscProd": "IPB-3 30CPR","DscDitta": "BIO STILOGIT PHARMACEUTIC. Srl","FFt": 25,"FPz": 38,"FFatt": 1005,"FFatt_D": 37.37,"FPezzi": 57,"FPezzi_D": 35.71,"FQuota": 0.71,"FPrezzo": 17.63,"CFt": 20,"CPz": 44,"CFatt": 116.26,"CFatt_D": 18.76,"CPezzi": 6,"CPezzi_D": 12.5,"CQuota": 0.13,"CPrezzo": 18.39},
{"DscProd": "FORTILASE 20CPR","DscDitta": "MEDA PHARMA SpA","FFt": 26,"FPz": 18,"FFatt": 914.7,"FFatt_D": 13.49,"FPezzi": 70,"FPezzi_D": 12.9,"FQuota": 0.88,"FPrezzo": 13.07,"CFt": 123,"CPz": 122,"CFatt": 926,"CFatt_D": -2.11,"CPezzi": 67,"CPezzi_D": -1.11,"CQuota": 1.37,"CPrezzo": 13.87},
{"DscProd": "LEVIAPROST 30CPS","DscDitta": "ENFARMA Srl","FFt": 27,"FPz": 23,"FFatt": 891.2,"FFatt_D": -35.53,"FPezzi": 31,"FPezzi_D": -35.42,"FQuota": 0.39,"FPrezzo": 28.75,"CFt": 16,"CPz": 61,"CFatt": 166.27,"CFatt_D": 11.31,"CPezzi": 6,"CPezzi_D": 19.01,"CQuota": 0.11,"CPrezzo": 30.12},
{"DscProd": "XATRAL30CPR RIV 2,5MG","DscDitta": "SANOFI SpA","FFt": 28,"FPz": 35,"FFatt": 870.3,"FFatt_D": 28.57,"FPezzi": 90,"FPezzi_D": 28.57,"FQuota": 1.13,"FPrezzo": 9.67,"CFt": 23,"CPz": 29,"CFatt": 239,"CFatt_D": 26.01,"CPezzi": 25,"CPezzi_D": 25.52,"CQuota": 0.51,"CPrezzo": 9.66},
{"DscProd": "SABA16CPS MOLLI 320MG","DscDitta": "LAMPUGNANI FARMACEUTICI SpA","FFt": 29,"FPz": 22,"FFatt": 793.8,"FFatt_D": 23.53,"FPezzi": 42,"FPezzi_D": 23.53,"FQuota": 0.53,"FPrezzo": 18.9,"CFt": 61,"CPz": 51,"CFatt": 824.96,"CFatt_D": 6.55,"CPezzi": 44,"CPezzi_D": 6.56,"CQuota": 0.9,"CPrezzo": 18.86},
{"DscProd": "PROPOSTA MONO 30CPS","DscDitta": "NATURAL BRADEL Srl","FFt": 30,"FPz": 25,"FFatt": 781.2,"FFatt_D": -11.07,"FPezzi": 31,"FPezzi_D": -16.22,"FQuota": 0.39,"FPrezzo": 25.2,"CFt": 39,"CPz": 58,"CFatt": 255.56,"CFatt_D": -18.21,"CPezzi": 10,"CPezzi_D": -19.21,"CQuota": 0.2,"CPrezzo": 26.71},
{"DscProd": "PROSTAMEV PLUS 30CPS MOLLI","DscDitta": "FARMACEUTICA MEV","FFt": 31,"FPz": 57,"FFatt": 779.5,"FFatt_D": 50.63,"FPezzi": 35,"FPezzi_D": 52.17,"FQuota": 0.44,"FPrezzo": 22.27,"CFt": 111,"CPz": 12,"CFatt": 341.95,"CFatt_D": 52.98,"CPezzi": 14,"CPezzi_D": 52.04,"CQuota": 0.29,"CPrezzo": 24.15},
{"DscProd": "PROSCAR15CPR RIV 5MG","DscDitta": "MSD ITALIA Srl","FFt": 32,"FPz": 49,"FFatt": 772.31,"FFatt_D": -19.79,"FPezzi": 77,"FPezzi_D": -19.79,"FQuota": 0.96,"FPrezzo": 10.03,"CFt": 51,"CPz": 57,"CFatt": 550.01,"CFatt_D": 2.43,"CPezzi": 55,"CPezzi_D": 1.92,"CQuota": 1.13,"CPrezzo": 10.02},
{"DscProd": "FITOPROSTAT 60CPS VEGETALI","DscDitta": "SOLGAR IT. MULTINUTRIENT SpA","FFt": 33,"FPz": 24,"FFatt": 689.03,"FFatt_D": 154.12,"FPezzi": 11,"FPezzi_D": 175,"FQuota": 0.14,"FPrezzo": 62.64,"CFt": 8,"CPz": 49,"CFatt": 72.29,"CFatt_D": 211.32,"CPezzi": 1,"CPezzi_D": 200,"CQuota": 0.03,"CPrezzo": 55.37},
{"DscProd": "PROSTASOL FORTE 48CPS","DscDitta": "HERBOPLANET Srl","FFt": 34,"FPz": 17,"FFatt": 647.25,"FFatt_D": 88.15,"FPezzi": 30,"FPezzi_D": 87.5,"FQuota": 0.38,"FPrezzo": 21.57,"CFt": 121,"CPz": 28,"CFatt": 47.22,"CFatt_D": 32.36,"CPezzi": 2,"CPezzi_D": 23.08,"CQuota": 0.04,"CPrezzo": 22.26},
{"DscProd": "PROSTIDE15CPR RIV 5MG","DscDitta": "SIGMATAU IND.FARM.RIUNITE SpA","FFt": 35,"FPz": 29,"FFatt": 634.8,"FFatt_D": -6.25,"FPezzi": 60,"FPezzi_D": -6.25,"FQuota": 0.75,"FPrezzo": 10.58,"CFt": 31,"CPz": 78,"CFatt": 569.93,"CFatt_D": -1.8,"CPezzi": 54,"CPezzi_D": -2.04,"CQuota": 1.11,"CPrezzo": 10.58},
{"DscProd": "MEDIFLUSS 320 20CPR","DscDitta": "D.PH. FARMACEUTICI Dr. A.MOSCA","FFt": 36,"FPz": 45,"FFatt": 633.6,"FFatt_D": -65.67,"FPezzi": 32,"FPezzi_D": -65.59,"FQuota": 0.4,"FPrezzo": 19.8,"CFt": 9,"CPz": 9,"CFatt": 56.45,"CFatt_D": -47.16,"CPezzi": 3,"CPezzi_D": -44.19,"CQuota": 0.06,"CPrezzo": 20.65},
{"DscProd": "COMBODART30CPS 0,5MG+0,4MG","DscDitta": "GLAXOSMITHKLINE SpA","FFt": 37,"FPz": 31,"FFatt": 523.2,"FFatt_D": 60,"FPezzi": 16,"FPezzi_D": 60,"FQuota": 0.2,"FPrezzo": 32.7,"CFt": 58,"CPz": 16,"CFatt": 109.26,"CFatt_D": 126.85,"CPezzi": 3,"CPezzi_D": 94.59,"CQuota": 0.07,"CPrezzo": 32.48},
{"DscProd": "PRADIF20CPS 0,4MG RM","DscDitta": "BOEHRINGER INGELHEIM IT.SpA","FFt": 38,"FPz": 36,"FFatt": 463.08,"FFatt_D": 17.24,"FPezzi": 68,"FPezzi_D": 17.24,"FQuota": 0.85,"FPrezzo": 6.81,"CFt": 150,"CPz": 23,"CFatt": 539.27,"CFatt_D": -5.21,"CPezzi": 79,"CPezzi_D": -5.72,"CQuota": 1.63,"CPrezzo": 6.81},
{"DscProd": "TERAPROST14CPR DIV 5MG","DscDitta": "MALESCI SpA IST.FARMACOBIOL.","FFt": 39,"FPz": 27,"FFatt": 447.36,"FFatt_D": 60,"FPezzi": 96,"FPezzi_D": 60,"FQuota": 1.2,"FPrezzo": 4.66,"CFt": 40,"CPz": 8,"CFatt": 386.96,"CFatt_D": 0.93,"CPezzi": 83,"CPezzi_D": 0.55,"CQuota": 1.7,"CPrezzo": 4.66},
{"DscProd": "UNOPROST14CPR DIV 5MG","DscDitta": "LABORATORI GUIDOTTI SpA","FFt": 40,"FPz": 30,"FFatt": 424.06,"FFatt_D": 15.19,"FPezzi": 91,"FPezzi_D": 15.19,"FQuota": 1.14,"FPrezzo": 4.66,"CFt": 7,"CPz": 18,"CFatt": 272.59,"CFatt_D": 9.15,"CPezzi": 59,"CPezzi_D": 9.42,"CQuota": 1.2,"CPrezzo": 4.66},
{"DscProd": "GSE PRO MEN 60CPR","DscDitta": "PRODECO PHARMA Srl","FFt": 41,"FPz": 34,"FFatt": 415.35,"FFatt_D": -19.74,"FPezzi": 20,"FPezzi_D": -20,"FQuota": 0.25,"FPrezzo": 20.77,"CFt": 30,"CPz": 66,"CFatt": 36.4,"CFatt_D": 25,"CPezzi": 2,"CPezzi_D": 50,"CQuota": 0.03,"CPrezzo": 22.85},
{"DscProd": "PROXANA PLUS 15CPS MOLLI","DscDitta": "SIGMATAU IND.FARM.RIUNITE SpA","FFt": 42,"FPz": 52,"FFatt": 396,"FFatt_D": -29.56,"FPezzi": 21,"FPezzi_D": -30,"FQuota": 0.26,"FPrezzo": 18.86,"CFt": 28,"CPz": 111,"CFatt": 202.17,"CFatt_D": -38.83,"CPezzi": 10,"CPezzi_D": -40.15,"CQuota": 0.21,"CPrezzo": 20.14},
{"DscProd": "VANDAPROST 24CPS","DscDitta": "VANDA OMEOPATICI Srl","FFt": 43,"FPz": 59,"FFatt": 376.2,"FFatt_D": -24,"FPezzi": 18,"FPezzi_D": -28,"FQuota": 0.23,"FPrezzo": 20.9,"CFt": 152,"CPz": 120,"CFatt": 27.53,"CFatt_D": -4.67,"CPezzi": 1,"CPezzi_D": -29.41,"CQuota": 0.03,"CPrezzo": 20.76},
{"DscProd": "TERAZOSINA TEVA14CPR 5MG","DscDitta": "TEVA ITALIA Srl","FFt": 44,"FPz": 51,"FFatt": 343.54,"FFatt_D": 21.92,"FPezzi": 89,"FPezzi_D": 21.92,"FQuota": 1.11,"FPrezzo": 3.86,"CFt": 122,"CPz": 7,"CFatt": 195.62,"CFatt_D": -8.75,"CPezzi": 51,"CPezzi_D": -8.6,"CQuota": 1.04,"CPrezzo": 3.86},
{"DscProd": "OFUXAL30CPR 10MG RP","DscDitta": "LAMPUGNANI FARMACEUTICI SpA","FFt": 45,"FPz": 20,"FFatt": 333.64,"FFatt_D": 65.22,"FPezzi": 38,"FPezzi_D": 65.22,"FQuota": 0.48,"FPrezzo": 8.78,"CFt": 54,"CPz": 80,"CFatt": 122.61,"CFatt_D": 111.01,"CPezzi": 14,"CPezzi_D": 111.32,"CQuota": 0.29,"CPrezzo": 8.78},
{"DscProd": "PROSTIL FORTE 15CPS","DscDitta": "FARMITALIA Srl","FFt": 46,"FPz": 53,"FFatt": 321.85,"FFatt_D": -39.14,"FPezzi": 18,"FPezzi_D": -41.94,"FQuota": 0.23,"FPrezzo": 17.88,"CFt": 144,"CPz": 92,"CFatt": 49.21,"CFatt_D": 24.82,"CPezzi": 3,"CPezzi_D": 33.31,"CQuota": 0.06,"CPrezzo": 18.1},
{"DscProd": "PEAPROSTIL 16BUST OROSOLUBILI","DscDitta": "FARMITALIA Srl","FFt": 47,"FPz": 42,"FFatt": 297,"FFatt_D": 66.67,"FPezzi": 16,"FPezzi_D": 77.78,"FQuota": 0.2,"FPrezzo": 18.56,"CFt": 42,"CPz": 17,"CFatt": 161.77,"CFatt_D": 12.54,"CPezzi": 8,"CPezzi_D": 16.36,"CQuota": 0.16,"CPrezzo": 20.85},
{"DscProd": "ABINCOL 14STICK OROSOLUBILI","DscDitta": "AURORA LICENSING","FFt": 48,"FPz": 41,"FFatt": 287.85,"FFatt_D": null,"FPezzi": 16,"FPezzi_D": null,"FQuota": 0.2,"FPrezzo": 17.99,"CFt": 22,"CPz": 31,"CFatt": 74.64,"CFatt_D": null,"CPezzi": 4,"CPezzi_D": null,"CQuota": 0.08,"CPrezzo": 18.12},
{"DscProd": "URODIE14CPR 5MG","DscDitta": "SIT LABORATORIO FARMAC. Srl","FFt": 49,"FPz": 43,"FFatt": 287.82,"FFatt_D": -1.82,"FPezzi": 54,"FPezzi_D": -1.82,"FQuota": 0.68,"FPrezzo": 5.33,"CFt": 44,"CPz": 45,"CFatt": 139.83,"CFatt_D": -2.07,"CPezzi": 26,"CPezzi_D": -3.86,"CQuota": 0.54,"CPrezzo": 5.33},
{"DscProd": "URELAX PLUS 30CPS SOFTGEL","DscDitta": "ECUPHARMA Srl","FFt": 50,"FPz": 46,"FFatt": 270,"FFatt_D": 100,"FPezzi": 12,"FPezzi_D": 100,"FQuota": 0.15,"FPrezzo": 22.5,"CFt": 74,"CPz": 106,"CFatt": 67.63,"CFatt_D": 38.96,"CPezzi": 3,"CPezzi_D": 35.85,"CQuota": 0.06,"CPrezzo": 23.89},
{"DscProd": "ALFUZOSINA ZEN30CPR 10MG RP","DscDitta": "ZENTIVA ITALIA Srl","FFt": 51,"FPz": 58,"FFatt": 254.62,"FFatt_D": -27.5,"FPezzi": 29,"FPezzi_D": -27.5,"FQuota": 0.36,"FPrezzo": 8.78,"CFt": 27,"CPz": 107,"CFatt": 374.26,"CFatt_D": 8.03,"CPezzi": 43,"CPezzi_D": 8.51,"CQuota": 0.87,"CPrezzo": 8.78},
{"DscProd": "FINASTERIDE EG15CPR RIV 5MG","DscDitta": "EG SpA","FFt": 52,"FPz": 37,"FFatt": 242.4,"FFatt_D": -47.37,"FPezzi": 30,"FPezzi_D": -47.37,"FQuota": 0.38,"FPrezzo": 8.08,"CFt": 47,"CPz": 150,"CFatt": 529.76,"CFatt_D": 25.37,"CPezzi": 66,"CPezzi_D": 25.51,"CQuota": 1.35,"CPrezzo": 8.08},
{"DscProd": "LURA20CPS 0,4MG RM","DscDitta": "ECUPHARMA Srl","FFt": 53,"FPz": 47,"FFatt": 183,"FFatt_D": -28.57,"FPezzi": 25,"FPezzi_D": -28.57,"FQuota": 0.31,"FPrezzo": 7.32,"CFt": 66,"CPz": 53,"CFatt": 89.39,"CFatt_D": -14.92,"CPezzi": 12,"CPezzi_D": -17.24,"CQuota": 0.25,"CPrezzo": 7.31},
{"DscProd": "RECOPROX 30CPS MOLLI","DscDitta": "RECORDATI SpA","FFt": 54,"FPz": 48,"FFatt": 168.8,"FFatt_D": 719.42,"FPezzi": 8,"FPezzi_D": 700,"FQuota": 0.1,"FPrezzo": 21.1,"CFt": 82,"CPz": 113,"CFatt": 217.45,"CFatt_D": 35.44,"CPezzi": 10,"CPezzi_D": 37.13,"CQuota": 0.2,"CPrezzo": 22.35},
{"DscProd": "IPROBEN 30CPS","DscDitta": "OMEGA PHARMA Srl","FFt": 55,"FPz": 61,"FFatt": 157.25,"FFatt_D": 601.7,"FPezzi": 7,"FPezzi_D": 600,"FQuota": 0.09,"FPrezzo": 22.46,"CFt": 49,"CPz": 130,"CFatt": 135.98,"CFatt_D": 8.13,"CPezzi": 6,"CPezzi_D": 15.2,"CQuota": 0.12,"CPrezzo": 23.94},
{"DscProd": "PROSTA MU GOCCE 30ML","DscDitta": "MU Srl","FFt": 56,"FPz": 78,"FFatt": 149.99,"FFatt_D": -24.45,"FPezzi": 10,"FPezzi_D": -9.09,"FQuota": 0.13,"FPrezzo": 15,"CFt": 80,"CPz": 30,"CFatt": 12,"CFatt_D": -48.32,"CPezzi": 0.756,"CPezzi_D": -41.47,"CQuota": 0.02,"CPrezzo": 15.86},
{"DscProd": "TERAPROST10CPR DIV 2MG","DscDitta": "MALESCI SpA IST.FARMACOBIOL.","FFt": 57,"FPz": 50,"FFatt": 141.93,"FFatt_D": -6.56,"FPezzi": 57,"FPezzi_D": -6.56,"FQuota": 0.71,"FPrezzo": 2.49,"CFt": 55,"CPz": 42,"CFatt": 78.61,"CFatt_D": 27.79,"CPezzi": 32,"CPezzi_D": 27.79,"CQuota": 0.65,"CPrezzo": 2.49},
{"DscProd": "UROREC30CPS 4MG","DscDitta": "RECORDATI SpA","FFt": 58,"FPz": 66,"FFatt": 138.6,"FFatt_D": 28.57,"FPezzi": 18,"FPezzi_D": 28.57,"FQuota": 0.23,"FPrezzo": 7.7,"CFt": 64,"CPz": 54,"CFatt": 316.4,"CFatt_D": 24.09,"CPezzi": 41,"CPezzi_D": 23.6,"CQuota": 0.84,"CPrezzo": 7.7},
{"DscProd": "TAMSULOSIN TEVA20CPS 0,4MG RM","DscDitta": "TEVA ITALIA Srl","FFt": 59,"FPz": 33,"FFatt": 132.3,"FFatt_D": -31.82,"FPezzi": 30,"FPezzi_D": -31.82,"FQuota": 0.38,"FPrezzo": 4.41,"CFt": 45,"CPz": 93,"CFatt": 676.26,"CFatt_D": 27.34,"CPezzi": 153,"CPezzi_D": 26.75,"CQuota": 3.15,"CPrezzo": 4.41},
{"DscProd": "MONOSELECT SABAL 30CPS","DscDitta": "PHARMEXTRACTA Srl","FFt": 60,"FPz": 75,"FFatt": 127.8,"FFatt_D": 12.4,"FPezzi": 8,"FPezzi_D": 14.29,"FQuota": 0.1,"FPrezzo": 15.97,"CFt": 25,"CPz": 144,"CFatt": 31.66,"CFatt_D": -8.39,"CPezzi": 2,"CPezzi_D": 0,"CQuota": 0.04,"CPrezzo": 17.19},
{"DscProd": "BENUR20CPR DIV 4MG","DscDitta": "PFIZER ITALIA Srl","FFt": 61,"FPz": 56,"FFatt": 127.2,"FFatt_D": null,"FPezzi": 15,"FPezzi_D": null,"FQuota": 0.19,"FPrezzo": 8.48,"CFt": 106,"CPz": 22,"CFatt": 387.63,"CFatt_D": 10.58,"CPezzi": 46,"CPezzi_D": 11.28,"CQuota": 0.94,"CPrezzo": 8.48},
{"DscProd": "PERLAPROST 14PRL","DscDitta": "NALKEIN PHARMA Srl","FFt": 62,"FPz": 87,"FFatt": 126.95,"FFatt_D": -54.6,"FPezzi": 6,"FPezzi_D": -53.85,"FQuota": 0.08,"FPrezzo": 21.16,"CFt": 24,"CPz": 74,"CFatt": 101.01,"CFatt_D": 178.06,"CPezzi": 4,"CPezzi_D": 146.15,"CQuota": 0.09,"CPrezzo": 22.99},
{"DscProd": "PROSTABEN COMPLEX 30CPS","DscDitta": "COSVAL SpA","FFt": 63,"FPz": 54,"FFatt": 119.2,"FFatt_D": -31.96,"FPezzi": 8,"FPezzi_D": -33.33,"FQuota": 0.1,"FPrezzo": 14.9,"CFt": 37,"CPz": 87,"CFatt": 5.17,"CFatt_D": -40.13,"CPezzi": 0.347,"CPezzi_D": -40.51,"CQuota": 0.01,"CPrezzo": 14.88},
{"DscProd": "PROSTADEP PLUS 20CPS NF","DscDitta": "ERBOZETA SpA","FFt": 64,"FPz": 60,"FFatt": 115.26,"FFatt_D": 103.93,"FPezzi": 6,"FPezzi_D": 100,"FQuota": 0.08,"FPrezzo": 19.21,"CFt": 107,"CPz": 116,"CFatt": 132.41,"CFatt_D": 29.5,"CPezzi": 6,"CPezzi_D": 19.01,"CQuota": 0.13,"CPrezzo": 20.4},
{"DscProd": "SERPENS16CPS 320MG","DscDitta": "LISAPHARMA SpA","FFt": 65,"FPz": 63,"FFatt": 111,"FFatt_D": null,"FPezzi": 6,"FPezzi_D": null,"FQuota": 0.08,"FPrezzo": 18.5,"CFt": 62,"CPz": 126,"CFatt": 83.49,"CFatt_D": 622.06,"CPezzi": 5,"CPezzi_D": 700,"CQuota": 0.09,"CPrezzo": 18.5},
{"DscProd": "ALFUZOSINA RAT30CPR 10MG RP","DscDitta": "RATIOPHARM ITALIA Srl","FFt": 66,"FPz": 55,"FFatt": 105.36,"FFatt_D": -50,"FPezzi": 12,"FPezzi_D": -50,"FQuota": 0.15,"FPrezzo": 8.78,"CFt": 156,"CPz": 20,"CFatt": 153.91,"CFatt_D": 33.8,"CPezzi": 18,"CPezzi_D": 36.28,"CQuota": 0.36,"CPrezzo": 8.78},
{"DscProd": "APROSTEN 30CPR","DscDitta": "OMEGA PHARMA Srl","FFt": 67,"FPz": 62,"FFatt": 90.25,"FFatt_D": -48.72,"FPezzi": 5,"FPezzi_D": -37.5,"FQuota": 0.06,"FPrezzo": 18.05,"CFt": 67,"CPz": 47,"CFatt": 94.74,"CFatt_D": 18.44,"CPezzi": 4,"CPezzi_D": 14.27,"CQuota": 0.08,"CPrezzo": 23.12},
{"DscProd": "TRICAPSURES 60CPS","DscDitta": "SAFI MEDICAL CARE Srl","FFt": 68,"FPz": 64,"FFatt": 83.5,"FFatt_D": 0.12,"FPezzi": 3,"FPezzi_D": 0,"FQuota": 0.04,"FPrezzo": 27.83,"CFt": 148,"CPz": 117,"CFatt": 25.06,"CFatt_D": -7.67,"CPezzi": 0.848,"CPezzi_D": -7.49,"CQuota": 0.02,"CPrezzo": 29.55},
{"DscProd": "FERPROST FAST 14BUST STICK","DscDitta": "FERPHARMA Srl","FFt": 69,"FPz": 65,"FFatt": 82.7,"FFatt_D": null,"FPezzi": 6,"FPezzi_D": null,"FQuota": 0.08,"FPrezzo": 13.78,"CFt": 78,"CPz": 119,"CFatt": 22.11,"CFatt_D": -3.07,"CPezzi": 2,"CPezzi_D": 20,"CQuota": 0.03,"CPrezzo": 13.73},
{"DscProd": "VITAPROST FORTE 45CPS","DscDitta": "GLOBAL PHARMA Srl","FFt": 70,"FPz": 69,"FFatt": 79.2,"FFatt_D": 33.33,"FPezzi": 4,"FPezzi_D": 33.33,"FQuota": 0.05,"FPrezzo": 19.8,"CFt": 53,"CPz": 127,"CFatt": 3.37,"CFatt_D": 2.17,"CPezzi": 0.17,"CPezzi_D": 2,"CQuota": 0,"CPrezzo": 19.8},
{"DscProd": "PROSTVIN 60CPR","DscDitta": "ERBENOBILI Srl","FFt": 71,"FPz": 93,"FFatt": 78.55,"FFatt_D": -69.9,"FPezzi": 3,"FPezzi_D": -70,"FQuota": 0.04,"FPrezzo": 26.18,"CFt": 130,"CPz": 124,"CFatt": 3.32,"CFatt_D": -74.56,"CPezzi": 0.127,"CPezzi_D": -74.6,"CQuota": 0,"CPrezzo": 26.18},
{"DscProd": "IBP PLUS 30CPR","DscDitta": "FITOPROJECT Srl","FFt": 72,"FPz": 67,"FFatt": 72,"FFatt_D": 33.33,"FPezzi": 4,"FPezzi_D": 33.33,"FQuota": 0.05,"FPrezzo": 18,"CFt": 113,"CPz": 152,"CFatt": 46.5,"CFatt_D": -30.67,"CPezzi": 2,"CPezzi_D": -41.46,"CQuota": 0.05,"CPrezzo": 19.44},
{"DscProd": "DOLIXIN 30CPR","DscDitta": "PRIUS PHARMA Srl","FFt": 73,"FPz": 80,"FFatt": 63.25,"FFatt_D": null,"FPezzi": 3,"FPezzi_D": null,"FQuota": 0.04,"FPrezzo": 21.08,"CFt": 65,"CPz": 25,"CFatt": 11.76,"CFatt_D": null,"CPezzi": 0.536,"CPezzi_D": null,"CQuota": 0.01,"CPrezzo": 21.95},
{"DscProd": "PROSTAPLANT60CPS 160MG+120MG","DscDitta": "DR.WILLMAR SCHWABE GmbH&CO.KG","FFt": 74,"FPz": 81,"FFatt": 59.7,"FFatt_D": 50,"FPezzi": 3,"FPezzi_D": 50,"FQuota": 0.04,"FPrezzo": 19.9,"CFt": 154,"CPz": 27,"CFatt": 170.92,"CFatt_D": -48.95,"CPezzi": 9,"CPezzi_D": -46.8,"CQuota": 0.18,"CPrezzo": 19.85},
{"DscProd": "BOTAM20CPS 0,4MG RM","DscDitta": "ITALIAN DEVICES Srl","FFt": 75,"FPz": 70,"FFatt": 59.07,"FFatt_D": null,"FPezzi": 11,"FPezzi_D": null,"FQuota": 0.14,"FPrezzo": 5.37,"CFt": 138,"CPz": 55,"CFatt": 22.11,"CFatt_D": 266.01,"CPezzi": 4,"CPezzi_D": 255.56,"CQuota": 0.08,"CPrezzo": 5.37},
{"DscProd": "NEVRIDOL 400 40CPR","DscDitta": "SHEDIR PHARMA Srl Unipersonale","FFt": 76,"FPz": 72,"FFatt": 52.6,"FFatt_D": null,"FPezzi": 2,"FPezzi_D": null,"FQuota": 0.03,"FPrezzo": 26.3,"CFt": 57,"CPz": 64,"CFatt": 12.95,"CFatt_D": null,"CPezzi": 0.468,"CPezzi_D": null,"CQuota": 0.01,"CPrezzo": 27.67},
{"DscProd": "PROSTADEP 30CPS","DscDitta": "ERBOZETA SpA","FFt": 77,"FPz": 92,"FFatt": 51.15,"FFatt_D": 50.44,"FPezzi": 3,"FPezzi_D": 50,"FQuota": 0.04,"FPrezzo": 17.05,"CFt": 120,"CPz": 104,"CFatt": 56.17,"CFatt_D": 11.8,"CPezzi": 3,"CPezzi_D": 12.5,"CQuota": 0.06,"CPrezzo": 18.77},
{"DscProd": "TERAZOSINA DOC14CPR DIV 5MG","DscDitta": "DOC GENERICI Srl","FFt": 78,"FPz": 68,"FFatt": 50.18,"FFatt_D": 225,"FPezzi": 13,"FPezzi_D": 225,"FQuota": 0.16,"FPrezzo": 3.86,"CFt": 48,"CPz": 151,"CFatt": 91.35,"CFatt_D": 0.99,"CPezzi": 24,"CPezzi_D": 2.47,"CQuota": 0.49,"CPrezzo": 3.86},
{"DscProd": "PROSTAGAN 30CPS","DscDitta": "MORGANCEUTICAL Srl","FFt": 79,"FPz": 71,"FFatt": 48.6,"FFatt_D": -40,"FPezzi": 3,"FPezzi_D": -40,"FQuota": 0.04,"FPrezzo": 16.2,"CFt": 90,"CPz": 24,"CFatt": 41.94,"CFatt_D": -43.46,"CPezzi": 2,"CPezzi_D": -53.4,"CQuota": 0.05,"CPrezzo": 17.74},
{"DscProd": "TERAZOSINA TEVA30CPR 2MG","DscDitta": "TEVA ITALIA Srl","FFt": 80,"FPz": 73,"FFatt": 41.14,"FFatt_D": -13.75,"FPezzi": 5,"FPezzi_D": 0,"FQuota": 0.06,"FPrezzo": 8.23,"CFt": 92,"CPz": 65,"CFatt": 137.48,"CFatt_D": -19.64,"CPezzi": 16,"CPezzi_D": -10.9,"CQuota": 0.33,"CPrezzo": 8.48},
{"DscProd": "FINASTERIDE MY15CPR RIV 5MG","DscDitta": "MYLAN SpA","FFt": 81,"FPz": 74,"FFatt": 40.4,"FFatt_D": null,"FPezzi": 5,"FPezzi_D": null,"FQuota": 0.06,"FPrezzo": 8.08,"CFt": 33,"CPz": 129,"CFatt": 738.95,"CFatt_D": -5.55,"CPezzi": 91,"CPezzi_D": -6,"CQuota": 1.88,"CPrezzo": 8.08},
{"DscProd": "PIGENIL60CPS MOLLI 50MG","DscDitta": "PHARMAFAR Srl","FFt": 82,"FPz": 77,"FFatt": 39.8,"FFatt_D": 0,"FPezzi": 1,"FPezzi_D": 0,"FQuota": 0.01,"FPrezzo": 39.8,"CFt": 151,"CPz": 135,"CFatt": 153.83,"CFatt_D": -14.04,"CPezzi": 4,"CPezzi_D": -18.64,"CQuota": 0.08,"CPrezzo": 39.78},
{"DscProd": "NOVA PROST 30CPS SOFTGEL","DscDitta": "NOVA ARGENTIA SpA","FFt": 83,"FPz": 79,"FFatt": 37.8,"FFatt_D": null,"FPezzi": 2,"FPezzi_D": null,"FQuota": 0.03,"FPrezzo": 18.9,"CFt": 50,"CPz": 138,"CFatt": 5.41,"CFatt_D": null,"CPezzi": 0.273,"CPezzi_D": null,"CQuota": 0.01,"CPrezzo": 19.78},
{"DscProd": "PROSTASER 30CPR","DscDitta": "DIFASS INTERNATIONAL Srl","FFt": 84,"FPz": 76,"FFatt": 34.22,"FFatt_D": null,"FPezzi": 2,"FPezzi_D": null,"FQuota": 0.03,"FPrezzo": 17.11,"CFt": 146,"CPz": 156,"CFatt": 48.73,"CFatt_D": 13.88,"CPezzi": 3,"CPezzi_D": 22.03,"CQuota": 0.06,"CPrezzo": 18.06},
{"DscProd": "PROSTAFORCE 60CPS VOGEL","DscDitta": "ANFATIS SpA","FFt": 85,"FPz": 83,"FFatt": 33.25,"FFatt_D": null,"FPezzi": 1,"FPezzi_D": null,"FQuota": 0.01,"FPrezzo": 33.25,"CFt": 104,"CPz": 48,"CFatt": 20.39,"CFatt_D": -34.36,"CPezzi": 0.604,"CPezzi_D": -34.11,"CQuota": 0.01,"CPrezzo": 33.73},
{"DscProd": "LONGLIFE ASTAXANTHIN 30PRL VEG","DscDitta": "PHOENIX Srl - LONGLIFE","FFt": 86,"FPz": 84,"FFatt": 30.59,"FFatt_D": -69.47,"FPezzi": 2,"FPezzi_D": -66.67,"FQuota": 0.03,"FPrezzo": 15.29,"CFt": 99,"CPz": 62,"CFatt": 15.71,"CFatt_D": -46.14,"CPezzi": 0.933,"CPezzi_D": -46.69,"CQuota": 0.02,"CPrezzo": 16.83},
{"DscProd": "UNOPROST10CPR DIV 2MG","DscDitta": "LABORATORI GUIDOTTI SpA","FFt": 87,"FPz": 86,"FFatt": 24.9,"FFatt_D": -47.37,"FPezzi": 10,"FPezzi_D": -47.37,"FQuota": 0.13,"FPrezzo": 2.49,"CFt": 36,"CPz": 67,"CFatt": 21.68,"CFatt_D": 11.98,"CPezzi": 9,"CPezzi_D": 14.29,"CQuota": 0.18,"CPrezzo": 2.49},
{"DscProd": "SAW PALMETTO 60CPS","DscDitta": "NATURAL POINT Srl","FFt": 88,"FPz": 88,"FFatt": 21.42,"FFatt_D": -33.33,"FPezzi": 2,"FPezzi_D": -33.33,"FQuota": 0.03,"FPrezzo": 10.71,"CFt": 77,"CPz": 75,"CFatt": 2.2,"CFatt_D": -64.84,"CPezzi": 0.21,"CPezzi_D": -61.23,"CQuota": 0,"CPrezzo": 10.44},
{"DscProd": "LICOSER 30CPR","DscDitta": "BREA Srl","FFt": 89,"FPz": 82,"FFatt": 20.4,"FFatt_D": null,"FPezzi": 1,"FPezzi_D": null,"FQuota": 0.01,"FPrezzo": 20.4,"CFt": 158,"CPz": 82,"CFatt": 2.72,"CFatt_D": -62.05,"CPezzi": 0.129,"CPezzi_D": -61.3,"CQuota": 0,"CPrezzo": 21.14},
{"DscProd": "PROSTAMEV 30CPR","DscDitta": "FARMACEUTICA MEV","FFt": 90,"FPz": 85,"FFatt": 19.8,"FFatt_D": -50,"FPezzi": 1,"FPezzi_D": -50,"FQuota": 0.01,"FPrezzo": 19.8,"CFt": 108,"CPz": 99,"CFatt": 74.39,"CFatt_D": 5.86,"CPezzi": 3,"CPezzi_D": -6.51,"CQuota": 0.07,"CPrezzo": 21.8},
{"DscProd": "PROSTAVIR 30CPR","DscDitta": "ABROS Srl","FFt": 91,"FPz": 89,"FFatt": 19.8,"FFatt_D": null,"FPezzi": 1,"FPezzi_D": null,"FQuota": 0.01,"FPrezzo": 19.8,"CFt": 147,"CPz": 102,"CFatt": 29.87,"CFatt_D": -31.98,"CPezzi": 1,"CPezzi_D": -51.02,"CQuota": 0.03,"CPrezzo": 21.87},
{"DscProd": "TAMLIC20CPS 0,4MG RM","DscDitta": "EPIFARMA Srl","FFt": 92,"FPz": 90,"FFatt": 17.64,"FFatt_D": 33.33,"FPezzi": 4,"FPezzi_D": 33.33,"FQuota": 0.05,"FPrezzo": 4.41,"CFt": 46,"CPz": 114,"CFatt": 72.53,"CFatt_D": 53.76,"CPezzi": 16,"CPezzi_D": 49.42,"CQuota": 0.34,"CPrezzo": 4.41},
{"DscProd": "URODIE10CPR DIV 2MG","DscDitta": "SIT LABORATORIO FARMAC. Srl","FFt": 93,"FPz": 91,"FFatt": 16.98,"FFatt_D": -53.85,"FPezzi": 6,"FPezzi_D": -53.85,"FQuota": 0.08,"FPrezzo": 2.83,"CFt": 153,"CPz": 115,"CFatt": 29.4,"CFatt_D": 23.46,"CPezzi": 10,"CPezzi_D": 17.65,"CQuota": 0.21,"CPrezzo": 2.82},
{"DscProd": "LINFOSER 20CPR","DscDitta": "LEVANPHARMA Srl","FFt": 94,"FPz": 94,"FFatt": 16.9,"FFatt_D": null,"FPezzi": 1,"FPezzi_D": null,"FQuota": 0.01,"FPrezzo": 16.9,"CFt": 84,"CPz": 132,"CFatt": 2.11,"CFatt_D": null,"CPezzi": 0.125,"CPezzi_D": null,"CQuota": 0,"CPrezzo": 16.9},
{"DscProd": "PROSTACARE 30CPS","DscDitta": "PHARMASUISSE LABORATORIES Srl","FFt": 95,"FPz": 95,"FFatt": 16.65,"FFatt_D": -51.32,"FPezzi": 1,"FPezzi_D": -50,"FQuota": 0.01,"FPrezzo": 16.65,"CFt": 129,"CPz": 134,"CFatt": 18.65,"CFatt_D": -46.31,"CPezzi": 1,"CPezzi_D": -50,"CQuota": 0.02,"CPrezzo": 17.74},
{"DscProd": "5ALFAPROST 30PRL","DscDitta": "FUTURE LIVE Srl","FFt": 96,"FPz": 96,"FFatt": 15.2,"FFatt_D": 0,"FPezzi": 1,"FPezzi_D": 0,"FQuota": 0.01,"FPrezzo": 15.2,"CFt": 34,"CPz": 148,"CFatt": 15.83,"CFatt_D": 44.88,"CPezzi": 0.991,"CPezzi_D": 39.91,"CQuota": 0.02,"CPrezzo": 15.97},
{"DscProd": "PROSTERBE 60OVAL 46,8G","DscDitta": "ESI SpA","FFt": 97,"FPz": 97,"FFatt": 14.25,"FFatt_D": 5.56,"FPezzi": 1,"FPezzi_D": 0,"FQuota": 0.01,"FPrezzo": 14.25,"CFt": 149,"CPz": 36,"CFatt": 1.27,"CFatt_D": -78.8,"CPezzi": 0.087,"CPezzi_D": -81.02,"CQuota": 0,"CPrezzo": 14.63},
{"DscProd": "PROSTABIO 30CPS","DscDitta": "LANOVA FARMACEUTICI Srl","FFt": 98,"FPz": 98,"FFatt": 13.41,"FFatt_D": null,"FPezzi": 1,"FPezzi_D": null,"FQuota": 0.01,"FPrezzo": 13.41,"CFt": 135,"CPz": 37,"CFatt": 1.73,"CFatt_D": 179.43,"CPezzi": 0.121,"CPezzi_D": 190.4,"CQuota": 0,"CPrezzo": 14.29},
{"DscProd": "BODY SPRING SERENOA REP 50CPS","DscDitta": "ANGELINI SpA","FFt": 99,"FPz": 99,"FFatt": 12.5,"FFatt_D": 5.04,"FPezzi": 1,"FPezzi_D": 0,"FQuota": 0.01,"FPrezzo": 12.5,"CFt": 72,"CPz": 46,"CFatt": 56.76,"CFatt_D": 60.08,"CPezzi": 4,"CPezzi_D": 41.18,"CQuota": 0.09,"CPrezzo": 12.95},
{"DscProd": "OLIO SEMI ZUCCA ARKOCAPS 60CPS","DscDitta": "ARKOFARM Srl","FFt": 100,"FPz": 100,"FFatt": 12.2,"FFatt_D": null,"FPezzi": 1,"FPezzi_D": null,"FQuota": 0.01,"FPrezzo": 12.2,"CFt": 142,"CPz": 50,"CFatt": 11.14,"CFatt_D": -49.01,"CPezzi": 0.836,"CPezzi_D": -51.06,"CQuota": 0.02,"CPrezzo": 13.33},
{"DscProd": "ORTICA RX ARKOCAPSULE 45CPS","DscDitta": "ARKOFARM Srl","FFt": 101,"FPz": 101,"FFatt": 12.15,"FFatt_D": null,"FPezzi": 1,"FPezzi_D": null,"FQuota": 0.01,"FPrezzo": 12.15,"CFt": 116,"CPz": 77,"CFatt": 16.11,"CFatt_D": -0.1,"CPezzi": 1,"CPezzi_D": -20,"CQuota": 0.03,"CPrezzo": 13.14},
{"DscProd": "FARALZIN30CPR 10MG RP","DscDitta": "NTC Srl","FFt": 102,"FPz": 102,"FFatt": 8.78,"FFatt_D": -50,"FPezzi": 1,"FPezzi_D": -50,"FQuota": 0.01,"FPrezzo": 8.78,"CFt": 140,"CPz": 84,"CFatt": 31.64,"CFatt_D": 49.28,"CPezzi": 4,"CPezzi_D": 65.52,"CQuota": 0.07,"CPrezzo": 8.78},
{"DscProd": "MITTOVAL30CPR RIV 2,5MG","DscDitta": "SANOFI SpA","FFt": 103,"FPz": 103,"FFatt": 0,"FFatt_D": -100,"FPezzi": 0,"FPezzi_D": -100,"FQuota": 0,"FPrezzo": null,"CFt": 155,"CPz": 90,"CFatt": 26.79,"CFatt_D": -20.61,"CPezzi": 3,"CPezzi_D": -14.29,"CQuota": 0.06,"CPrezzo": 9.67},
{"DscProd": "GENAPROST15CPR RIV 5MG","DscDitta": "NEOPHARMED GENTILI Srl","FFt": 104,"FPz": 104,"FFatt": 0,"FFatt_D": -100,"FPezzi": 0,"FPezzi_D": -100,"FQuota": 0,"FPrezzo": null,"CFt": 79,"CPz": 103,"CFatt": 60.5,"CFatt_D": -4.38,"CPezzi": 6,"CPezzi_D": -4,"CQuota": 0.12,"CPrezzo": 10.2},
{"DscProd": "UROFLUS10CPR 2MG","DscDitta": "S.F.GROUP Srl","FFt": 105,"FPz": 105,"FFatt": 0,"FFatt_D": -100,"FPezzi": 0,"FPezzi_D": -100,"FQuota": 0,"FPrezzo": null,"CFt": 126,"CPz": 108,"CFatt": 5.64,"CFatt_D": 264.05,"CPezzi": 2,"CPezzi_D": 220,"CQuota": 0.05,"CPrezzo": 2.48},
{"DscProd": "ALFUZOSINA EG30CPR 10MG RP","DscDitta": "EG SpA","FFt": 106,"FPz": 106,"FFatt": 0,"FFatt_D": -100,"FPezzi": 0,"FPezzi_D": -100,"FQuota": 0,"FPrezzo": null,"CFt": 143,"CPz": 133,"CFatt": 110.96,"CFatt_D": 76.37,"CPezzi": 13,"CPezzi_D": 81.4,"CQuota": 0.26,"CPrezzo": 8.78},
{"DscProd": "SILODYX30CPS 4MG","DscDitta": "TAKEDA ITALIA SpA","FFt": 107,"FPz": 107,"FFatt": 0,"FFatt_D": -100,"FPezzi": 0,"FPezzi_D": -100,"FQuota": 0,"FPrezzo": null,"CFt": 110,"CPz": 146,"CFatt": 102,"CFatt_D": 4.59,"CPezzi": 13,"CPezzi_D": 2.62,"CQuota": 0.27,"CPrezzo": 7.7},
{"DscProd": "FERPROST 15CPS","DscDitta": "FERPHARMA Srl","FFt": 108,"FPz": 108,"FFatt": 0,"FFatt_D": -100,"FPezzi": 0,"FPezzi_D": -100,"FQuota": 0,"FPrezzo": null,"CFt": 109,"CPz": 153,"CFatt": 52.98,"CFatt_D": -66.08,"CPezzi": 3,"CPezzi_D": -62.3,"CQuota": 0.06,"CPrezzo": 19.59},
{"DscProd": "MANDROGHEN 30CPR 750MG","DscDitta": "DIETOFARM SpA","FFt": 109,"FPz": 109,"FFatt": 0,"FFatt_D": -100,"FPezzi": 0,"FPezzi_D": -100,"FQuota": 0,"FPrezzo": null,"CFt": 127,"CPz": 154,"CFatt": 37.36,"CFatt_D": 20.71,"CPezzi": 2,"CPezzi_D": 17.07,"CQuota": 0.04,"CPrezzo": 18.16},
{"DscProd": "DIFAPROST INTEGRATORE 15CPR","DscDitta": "DIFASS INTERNATIONAL Srl","FFt": 110,"FPz": 110,"FFatt": 0,"FFatt_D": -100,"FPezzi": 0,"FPezzi_D": -100,"FQuota": 0,"FPrezzo": null,"CFt": 41,"CPz": 158,"CFatt": 38.98,"CFatt_D": -3.77,"CPezzi": 2,"CPezzi_D": -7.69,"CQuota": 0.04,"CPrezzo": 19},
{"DscProd": "Altre 124 referenze","DscDitta": "105 ditte coinvolte","FFt": 111,"FPz": 111,"FFatt": 0,"FFatt_D": -100,"FPezzi": 0,"FPezzi_D": -100,"FQuota": 0,"FPrezzo": 0,"CFt": 132,"CPz": 34,"CFatt": 376.67,"CFatt_D": -24.81,"CPezzi": 18,"CPezzi_D": -30.99,"CQuota": 0.38,"CPrezzo": 11.69},
{"DscProd": "TERAFLUSS30CPR DIV 2MG","DscDitta": "MEDA PHARMA SpA","FFt": 112,"FPz": 112,"FFatt": null,"FFatt_D": null,"FPezzi": null,"FPezzi_D": null,"FQuota": null,"FPrezzo": null,"CFt": 134,"CPz": 41,"CFatt": 18.16,"CFatt_D": 34.38,"CPezzi": 2,"CPezzi_D": 41.18,"CQuota": 0.04,"CPrezzo": 9.54},
{"DscProd": "TERAFLUSS28CPR DIV 5MG","DscDitta": "MEDA PHARMA SpA","FFt": 113,"FPz": 113,"FFatt": null,"FFatt_D": null,"FPezzi": null,"FPezzi_D": null,"FQuota": null,"FPrezzo": null,"CFt": 157,"CPz": 60,"CFatt": 83.78,"CFatt_D": 26.17,"CPezzi": 12,"CPezzi_D": 24.68,"CQuota": 0.25,"CPrezzo": 6.9},
{"DscProd": "PROSTATIL14CPR DIV 5MG","DscDitta": "S.F.GROUP Srl","FFt": 114,"FPz": 114,"FFatt": null,"FFatt_D": null,"FPezzi": null,"FPezzi_D": null,"FQuota": null,"FPrezzo": null,"CFt": 119,"CPz": 69,"CFatt": 18.38,"CFatt_D": -0.34,"CPezzi": 4,"CPezzi_D": 1.05,"CQuota": 0.08,"CPrezzo": 4.66},
{"DscProd": "TERAZOSINA ZEN14CPR DIV 5MG","DscDitta": "ABC FARMACEUTICI SpA","FFt": 115,"FPz": 115,"FFatt": null,"FFatt_D": null,"FPezzi": null,"FPezzi_D": null,"FQuota": null,"FPrezzo": null,"CFt": 141,"CPz": 72,"CFatt": 15.73,"CFatt_D": 1529.65,"CPezzi": 4,"CPezzi_D": 1500,"CQuota": 0.08,"CPrezzo": 3.86},
{"DscProd": "UROFLUS14CPR 5MG","DscDitta": "S.F.GROUP Srl","FFt": 116,"FPz": 116,"FFatt": null,"FFatt_D": null,"FPezzi": null,"FPezzi_D": null,"FQuota": null,"FPrezzo": null,"CFt": 60,"CPz": 79,"CFatt": 43.91,"CFatt_D": 58.36,"CPezzi": 9,"CPezzi_D": 51.05,"CQuota": 0.19,"CPrezzo": 4.66},
{"DscProd": "TERAZOSINA DOC10CPR DIV 2MG","DscDitta": "DOC GENERICI Srl","FFt": 117,"FPz": 117,"FFatt": null,"FFatt_D": null,"FPezzi": null,"FPezzi_D": null,"FQuota": null,"FPrezzo": null,"CFt": 102,"CPz": 105,"CFatt": 16.13,"CFatt_D": 3.34,"CPezzi": 8,"CPezzi_D": 5.49,"CQuota": 0.16,"CPrezzo": 2.06},
{"DscProd": "TERAZOSINA MY10CPR 2MG","DscDitta": "MYLAN SpA","FFt": 118,"FPz": 118,"FFatt": null,"FFatt_D": null,"FPezzi": null,"FPezzi_D": null,"FQuota": null,"FPrezzo": null,"CFt": 124,"CPz": 109,"CFatt": 2.81,"CFatt_D": -0.93,"CPezzi": 1,"CPezzi_D": -27.27,"CQuota": 0.03,"CPrezzo": 2.06},
{"DscProd": "TERAZOSINA HEXAL14CPR 5MG","DscDitta": "SANDOZ SpA","FFt": 119,"FPz": 119,"FFatt": null,"FFatt_D": null,"FPezzi": null,"FPezzi_D": null,"FQuota": null,"FPrezzo": null,"CFt": 91,"CPz": 110,"CFatt": 32.22,"CFatt_D": 55.32,"CPezzi": 8,"CPezzi_D": 48.84,"CQuota": 0.17,"CPrezzo": 3.86},
{"DscProd": "ANTUNES20CPS 0,4MG RM","DscDitta": "SO.SE.PHARM Srl","FFt": 120,"FPz": 120,"FFatt": null,"FFatt_D": null,"FPezzi": null,"FPezzi_D": null,"FQuota": null,"FPrezzo": null,"CFt": 93,"CPz": 112,"CFatt": 77.5,"CFatt_D": 93.66,"CPezzi": 18,"CPezzi_D": 98.17,"CQuota": 0.36,"CPrezzo": 4.41},
{"DscProd": "TAMSULOSINA EG20CPS 0,4MG RM","DscDitta": "EG SpA","FFt": 121,"FPz": 121,"FFatt": null,"FFatt_D": null,"FPezzi": null,"FPezzi_D": null,"FQuota": null,"FPrezzo": null,"CFt": 139,"CPz": 140,"CFatt": 356.46,"CFatt_D": 9.63,"CPezzi": 81,"CPezzi_D": 9.77,"CQuota": 1.66,"CPrezzo": 4.41},
{"DscProd": "TAMSULOSIN DOC20CPS 0,4MG RM","DscDitta": "DOC GENERICI Srl","FFt": 122,"FPz": 122,"FFatt": null,"FFatt_D": null,"FPezzi": null,"FPezzi_D": null,"FQuota": null,"FPrezzo": null,"CFt": 43,"CPz": 141,"CFatt": 224.95,"CFatt_D": 43.16,"CPezzi": 51,"CPezzi_D": 43.15,"CQuota": 1.05,"CPrezzo": 4.41},
{"DscProd": "TAMSULOSINA SAN20CPS 0,4MG RM","DscDitta": "SANDOZ SpA","FFt": 123,"FPz": 123,"FFatt": null,"FFatt_D": null,"FPezzi": null,"FPezzi_D": null,"FQuota": null,"FPrezzo": null,"CFt": 103,"CPz": 143,"CFatt": 421.96,"CFatt_D": 22.62,"CPezzi": 96,"CPezzi_D": 23.01,"CQuota": 1.96,"CPrezzo": 4.41},
{"DscProd": "TAMSULOSINA ZEN20CPS 0,4MG RM","DscDitta": "ZENTIVA ITALIA Srl","FFt": 124,"FPz": 124,"FFatt": null,"FFatt_D": null,"FPezzi": null,"FPezzi_D": null,"FQuota": null,"FPrezzo": null,"CFt": 133,"CPz": 147,"CFatt": 30.92,"CFatt_D": -9.46,"CPezzi": 7,"CPezzi_D": -9.68,"CQuota": 0.14,"CPrezzo": 4.41},
{"DscProd": "TAMSULOSINA HEX20CPS 0,4MG RM","DscDitta": "SANDOZ SpA","FFt": 125,"FPz": 125,"FFatt": null,"FFatt_D": null,"FPezzi": null,"FPezzi_D": null,"FQuota": null,"FPrezzo": null,"CFt": 68,"CPz": 149,"CFatt": 3.06,"CFatt_D": -87.93,"CPezzi": 0.694,"CPezzi_D": -87.93,"CQuota": 0.01,"CPrezzo": 4.41},
{"DscProd": "TAMSULOSINA AUR20CPS 0,4MG RM","DscDitta": "AUROBINDO PHARMA ITALIA Srl","FFt": 126,"FPz": 126,"FFatt": null,"FFatt_D": null,"FPezzi": null,"FPezzi_D": null,"FQuota": null,"FPrezzo": null,"CFt": 137,"CPz": 155,"CFatt": 41.04,"CFatt_D": null,"CPezzi": 9,"CPezzi_D": null,"CQuota": 0.19,"CPrezzo": 4.41},
{"DscProd": "TAMSULOSIN RAN20CPS 0,4MG RP","DscDitta": "RANBAXY ITALIA SpA","FFt": 127,"FPz": 127,"FFatt": null,"FFatt_D": null,"FPezzi": null,"FPezzi_D": null,"FQuota": null,"FPrezzo": null,"CFt": 145,"CPz": 33,"CFatt": 36.61,"CFatt_D": -15.94,"CPezzi": 8,"CPezzi_D": -18.99,"CQuota": 0.17,"CPrezzo": 4.41},
{"DscProd": "FINASTERIDE HEX15CPR RIV 5MG","DscDitta": "SANDOZ SpA","FFt": 128,"FPz": 128,"FFatt": null,"FFatt_D": null,"FPezzi": null,"FPezzi_D": null,"FQuota": null,"FPrezzo": null,"CFt": 75,"CPz": 43,"CFatt": 0.58,"CFatt_D": -93.65,"CPezzi": 0.071,"CPezzi_D": -93.69,"CQuota": 0,"CPrezzo": 8.08},
{"DscProd": "ALFUZOSINA HEX30CPR 10MG RP","DscDitta": "SANDOZ SpA","FFt": 129,"FPz": 129,"FFatt": null,"FFatt_D": null,"FPezzi": null,"FPezzi_D": null,"FQuota": null,"FPrezzo": null,"CFt": 69,"CPz": 91,"CFatt": 47.9,"CFatt_D": 52.25,"CPezzi": 5,"CPezzi_D": 39.53,"CQuota": 0.11,"CPrezzo": 8.78},
{"DscProd": "FINASTERIDE SAND15CPR RIV 5MG","DscDitta": "SANDOZ SpA","FFt": 130,"FPz": 130,"FFatt": null,"FFatt_D": null,"FPezzi": null,"FPezzi_D": null,"FQuota": null,"FPrezzo": null,"CFt": 87,"CPz": 95,"CFatt": 88.08,"CFatt_D": 351.09,"CPezzi": 11,"CPezzi_D": 355.17,"CQuota": 0.22,"CPrezzo": 8.08},
{"DscProd": "FINASTERIDE ZEN15CPR RIV 5MG","DscDitta": "ZENTIVA ITALIA Srl","FFt": 131,"FPz": 131,"FFatt": null,"FFatt_D": null,"FPezzi": null,"FPezzi_D": null,"FQuota": null,"FPrezzo": null,"CFt": 85,"CPz": 101,"CFatt": 5.61,"CFatt_D": 11.18,"CPezzi": 0.694,"CPezzi_D": 11.04,"CQuota": 0.01,"CPrezzo": 8.08},
{"DscProd": "ASTERID15CPR RIV 5MG","DscDitta": "EPIFARMA Srl","FFt": 132,"FPz": 132,"FFatt": null,"FFatt_D": null,"FPezzi": null,"FPezzi_D": null,"FQuota": null,"FPrezzo": null,"CFt": 136,"CPz": 118,"CFatt": 35.08,"CFatt_D": 189.8,"CPezzi": 4,"CPezzi_D": 166.67,"CQuota": 0.09,"CPrezzo": 8.08},
{"DscProd": "RIDESTIN15CPR RIV 5MG","DscDitta": "S.F.GROUP Srl","FFt": 133,"FPz": 133,"FFatt": null,"FFatt_D": null,"FPezzi": null,"FPezzi_D": null,"FQuota": null,"FPrezzo": null,"CFt": 95,"CPz": 136,"CFatt": 26.21,"CFatt_D": 135.9,"CPezzi": 3,"CPezzi_D": 118.18,"CQuota": 0.07,"CPrezzo": 8.08},
{"DscProd": "FINASTERIDE DOC15CPR RIV 5MG","DscDitta": "DOC GENERICI Srl","FFt": 134,"FPz": 134,"FFatt": null,"FFatt_D": null,"FPezzi": null,"FPezzi_D": null,"FQuota": null,"FPrezzo": null,"CFt": 114,"CPz": 137,"CFatt": 34.62,"CFatt_D": -50.08,"CPezzi": 4,"CPezzi_D": -53.4,"CQuota": 0.09,"CPrezzo": 8.08},
{"DscProd": "ALFUZOSINA DOC30CPR 10MG RP","DscDitta": "DOC GENERICI Srl","FFt": 135,"FPz": 135,"FFatt": null,"FFatt_D": null,"FPezzi": null,"FPezzi_D": null,"FQuota": null,"FPrezzo": null,"CFt": 112,"CPz": 139,"CFatt": 46.57,"CFatt_D": 3.49,"CPezzi": 5,"CPezzi_D": -2.44,"CQuota": 0.11,"CPrezzo": 8.78},
{"DscProd": "KURBIS ZUCCA 30CPR DR BOHM","DscDitta": "ROSSLER Srl","FFt": 136,"FPz": 136,"FFatt": null,"FFatt_D": null,"FPezzi": null,"FPezzi_D": null,"FQuota": null,"FPrezzo": null,"CFt": 117,"CPz": 142,"CFatt": 19.89,"CFatt_D": -35.72,"CPezzi": 1,"CPezzi_D": -48.94,"CQuota": 0.03,"CPrezzo": 15.8},
{"DscProd": "RIDUPROST 30CPS","DscDitta": "BRG FARMACEUTICA Srl","FFt": 137,"FPz": 137,"FFatt": null,"FFatt_D": null,"FPezzi": null,"FPezzi_D": null,"FQuota": null,"FPrezzo": null,"CFt": 101,"CPz": 145,"CFatt": 24.61,"CFatt_D": -20.31,"CPezzi": 1,"CPezzi_D": -36.84,"CQuota": 0.03,"CPrezzo": 19.49},
{"DscProd": "VITAMEN 10FL 20ML","DscDitta": "BETA LAB.BIOLOGICO CHEMIOTERAP","FFt": 138,"FPz": 138,"FFatt": null,"FFatt_D": null,"FPezzi": null,"FPezzi_D": null,"FQuota": null,"FPrezzo": null,"CFt": 96,"CPz": 157,"CFatt": 79.23,"CFatt_D": -4.3,"CPezzi": 5,"CPezzi_D": -11.11,"CQuota": 0.11,"CPrezzo": 15},
{"DscProd": "SOMAPROST 16CPS","DscDitta": "GISSOMA Srl","FFt": 139,"FPz": 139,"FFatt": null,"FFatt_D": null,"FPezzi": null,"FPezzi_D": null,"FQuota": null,"FPrezzo": null,"CFt": 115,"CPz": 96,"CFatt": 29.32,"CFatt_D": 27.15,"CPezzi": 1,"CPezzi_D": -11.11,"CQuota": 0.03,"CPrezzo": 20.21},
{"DscProd": "SINPROST 30PRL","DscDitta": "RNE BIOFARMA","FFt": 140,"FPz": 140,"FFatt": null,"FFatt_D": null,"FPezzi": null,"FPezzi_D": null,"FQuota": null,"FPrezzo": null,"CFt": 86,"CPz": 86,"CFatt": 43.39,"CFatt_D": -35.36,"CPezzi": 2,"CPezzi_D": -20,"CQuota": 0.03,"CPrezzo": 26.82},
{"DscProd": "QTPROST 20CPS","DscDitta": "DOCET ITALIA Srl","FFt": 141,"FPz": 141,"FFatt": null,"FFatt_D": null,"FPezzi": null,"FPezzi_D": null,"FQuota": null,"FPrezzo": null,"CFt": 76,"CPz": 68,"CFatt": 32.15,"CFatt_D": -6.61,"CPezzi": 2,"CPezzi_D": 14.29,"CQuota": 0.03,"CPrezzo": 19.46},
{"DscProd": "NUTRIVA PROSTAPLUS 30SOFTGEL","DscDitta": "CABASSI & GIURIATI SpA","FFt": 142,"FPz": 142,"FFatt": null,"FFatt_D": null,"FPezzi": null,"FPezzi_D": null,"FQuota": null,"FPrezzo": null,"CFt": 56,"CPz": 100,"CFatt": 44.59,"CFatt_D": -39.25,"CPezzi": 1,"CPezzi_D": -60.66,"CQuota": 0.03,"CPrezzo": 32.5},
{"DscProd": "TRADAPROST 20CPS","DscDitta": "TRADAPHARMA D.o.o.","FFt": 143,"FPz": 143,"FFatt": null,"FFatt_D": null,"FPezzi": null,"FPezzi_D": null,"FQuota": null,"FPrezzo": null,"CFt": 73,"CPz": 56,"CFatt": 39.1,"CFatt_D": -44.82,"CPezzi": 2,"CPezzi_D": -47.83,"CQuota": 0.04,"CPrezzo": 18.28},
{"DscProd": "FAGRON SERENOA PERLE 30PRL","DscDitta": "FAGRON ITALIA Srl","FFt": 144,"FPz": 144,"FFatt": null,"FFatt_D": null,"FPezzi": null,"FPezzi_D": null,"FQuota": null,"FPrezzo": null,"CFt": 100,"CPz": 125,"CFatt": 212.8,"CFatt_D": -16.01,"CPezzi": 10,"CPezzi_D": -21.57,"CQuota": 0.21,"CPrezzo": 20.56},
{"DscProd": "PROGEPROST PLUS 15CPS","DscDitta": "PROGE FARM Srl","FFt": 145,"FPz": 145,"FFatt": null,"FFatt_D": null,"FPezzi": null,"FPezzi_D": null,"FQuota": null,"FPrezzo": null,"CFt": 105,"CPz": 131,"CFatt": 22.9,"CFatt_D": -48.23,"CPezzi": 1,"CPezzi_D": -61.29,"CQuota": 0.03,"CPrezzo": 16.96},
{"DscProd": "NOVIXON 16CPS SOFTGEL","DscDitta": "STARDEA Srl","FFt": 146,"FPz": 146,"FFatt": null,"FFatt_D": null,"FPezzi": null,"FPezzi_D": null,"FQuota": null,"FPrezzo": null,"CFt": 131,"CPz": 85,"CFatt": 66.9,"CFatt_D": -31.11,"CPezzi": 3,"CPezzi_D": -36.84,"CQuota": 0.06,"CPrezzo": 21.35},
{"DscProd": "PROSTAFLOG 30CPR","DscDitta": "NATURMED Srl","FFt": 147,"FPz": 147,"FFatt": null,"FFatt_D": null,"FPezzi": null,"FPezzi_D": null,"FQuota": null,"FPrezzo": null,"CFt": 83,"CPz": 73,"CFatt": 51.19,"CFatt_D": 1247.25,"CPezzi": 2,"CPezzi_D": 1100,"CQuota": 0.05,"CPrezzo": 23.18},
{"DscProd": "NUTRIPROST ONE 20CPS","DscDitta": "LAERBIUM PHARMA Srl","FFt": 148,"FPz": 148,"FFatt": null,"FFatt_D": null,"FPezzi": null,"FPezzi_D": null,"FQuota": null,"FPrezzo": null,"CFt": 63,"CPz": 76,"CFatt": 94.42,"CFatt_D": 7.12,"CPezzi": 4,"CPezzi_D": 7.87,"CQuota": 0.08,"CPrezzo": 23.72},
{"DscProd": "PROSTASI' 30CPR","DscDitta": "PHARMASI' Srl","FFt": 149,"FPz": 149,"FFatt": null,"FFatt_D": null,"FPezzi": null,"FPezzi_D": null,"FQuota": null,"FPrezzo": null,"CFt": 70,"CPz": 63,"CFatt": 46.58,"CFatt_D": 104.73,"CPezzi": 2,"CPezzi_D": 84.62,"CQuota": 0.05,"CPrezzo": 21},
{"DscProd": "FERPROST FORTE 15CPS MOLLI 2BL","DscDitta": "FERPHARMA Srl","FFt": 150,"FPz": 150,"FFatt": null,"FFatt_D": null,"FPezzi": null,"FPezzi_D": null,"FQuota": null,"FPrezzo": null,"CFt": 71,"CPz": 83,"CFatt": 288.16,"CFatt_D": -32.99,"CPezzi": 13,"CPezzi_D": -32.61,"CQuota": 0.27,"CPrezzo": 21.92},
{"DscProd": "LDF IPERPROST PLUS 30CPR","DscDitta": "LABORATORIO DELLA FARMACIA Srl","FFt": 151,"FPz": 151,"FFatt": null,"FFatt_D": null,"FPezzi": null,"FPezzi_D": null,"FQuota": null,"FPrezzo": null,"CFt": 125,"CPz": 88,"CFatt": 69.06,"CFatt_D": -31.96,"CPezzi": 6,"CPezzi_D": -32.09,"CQuota": 0.12,"CPrezzo": 11.48},
{"DscProd": "PROSTANOX 30CPR","DscDitta": "LABOREST ITALIA S.R.L.","FFt": 152,"FPz": 152,"FFatt": null,"FFatt_D": null,"FPezzi": null,"FPezzi_D": null,"FQuota": null,"FPrezzo": null,"CFt": 118,"CPz": 70,"CFatt": 234.33,"CFatt_D": 78.91,"CPezzi": 7,"CPezzi_D": 57.01,"CQuota": 0.14,"CPrezzo": 34.42},
{"DscProd": "MASSIGEN VITIPROST SOFT G30PRL","DscDitta": "MARCO VITI FARMACEUTICI SpA","FFt": 153,"FPz": 153,"FFatt": null,"FFatt_D": null,"FPezzi": null,"FPezzi_D": null,"FQuota": null,"FPrezzo": null,"CFt": 89,"CPz": 89,"CFatt": 48.99,"CFatt_D": 3010.49,"CPezzi": 3,"CPezzi_D": 3500,"CQuota": 0.06,"CPrezzo": 17.91},
{"DscProd": "PROSTALEX 30CPR","DscDitta": "CETRA ITALIA Srl","FFt": 154,"FPz": 154,"FFatt": null,"FFatt_D": null,"FPezzi": null,"FPezzi_D": null,"FQuota": null,"FPrezzo": null,"CFt": 88,"CPz": 71,"CFatt": 79.78,"CFatt_D": -5.72,"CPezzi": 3,"CPezzi_D": -14.29,"CQuota": 0.06,"CPrezzo": 26.03},
{"DscProd": "PROSTACTIV PLUS 20CPR","DscDitta": "SWISS PHARMA Srl","FFt": 155,"FPz": 155,"FFatt": null,"FFatt_D": null,"FPezzi": null,"FPezzi_D": null,"FQuota": null,"FPrezzo": null,"CFt": 94,"CPz": 94,"CFatt": 43,"CFatt_D": 48.84,"CPezzi": 2,"CPezzi_D": 14.29,"CQuota": 0.04,"CPrezzo": 19.79},
{"DscProd": "CURMANOX 15CPR","DscDitta": "ABI PHARMACEUTICAL Srl","FFt": 156,"FPz": 156,"FFatt": null,"FFatt_D": null,"FPezzi": null,"FPezzi_D": null,"FQuota": null,"FPrezzo": null,"CFt": 98,"CPz": 98,"CFatt": 96.1,"CFatt_D": -12.65,"CPezzi": 5,"CPezzi_D": -17.24,"CQuota": 0.11,"CPrezzo": 18.15},
{"DscProd": "ANDROPROX 700 15PRL SOFTGEL","DscDitta": "LABORATORI NUTRIPHYT Sas","FFt": 157,"FPz": 157,"FFatt": null,"FFatt_D": null,"FPezzi": null,"FPezzi_D": null,"FQuota": null,"FPrezzo": null,"CFt": 97,"CPz": 97,"CFatt": 32.7,"CFatt_D": 453.6,"CPezzi": 1,"CPezzi_D": 200,"CQuota": 0.03,"CPrezzo": 22.28},
{"DscProd": "REPEUREX 30CPR","DscDitta": "HAUORA MED Srl","FFt": 158,"FPz": 158,"FFatt": null,"FFatt_D": null,"FPezzi": null,"FPezzi_D": null,"FQuota": null,"FPrezzo": null,"CFt": 128,"CPz": 128,"CFatt": 53.59,"CFatt_D": 8830.95,"CPezzi": 3,"CPezzi_D": 7100,"CQuota": 0.06,"CPrezzo": 18.95} 
]}
