{"datiDettRef":[


 {"DscProd": "XENICAL84CPS 120MG","DscDitta": "ROCHE SpA","FFt": 1,"FPz": 1,"FFatt": 114.5,"FFatt_D": -80,"FPezzi": 1,"FPezzi_D": -80,"FQuota": 100,"FPrezzo": 114.5,"MFt": 1,"MPz": 1,"MFatt": 16.73,"MFatt_D": -15.28,"MPezzi": 0.147,"MPezzi_D": -15.86,"MQuota": 64.58,"MPrezzo": 114.11},
{"DscProd": "Altre 5 referenze","DscDitta": "6 ditte coinvolte","FFt": 2,"FPz": 2,"FFatt": 0,"FFatt_D": null,"FPezzi": 0,"FPezzi_D": null,"FQuota": 0,"FPrezzo": 0,"MFt": 2,"MPz": 2,"MFatt": 7.77,"MFatt_D": -22.51,"MPezzi": 0,"MPezzi_D": -100,"MQuota": 35.24,"MPrezzo": 65.66} 
]}
