{"datiDettRef":[


 {"DscProd": "ESTECLINOS GRAT 20BUST 225MG","DscDitta": "EDMOND PHARMA Srl","FFt": 1,"FPz": 1,"FFatt": 12.8,"FFatt_D": null,"FPezzi": 1,"FPezzi_D": null,"FQuota": 50,"FPrezzo": 12.8,"CFt": 2,"CPz": 2,"CFatt": 9.94,"CFatt_D": 832.14,"CPezzi": 0.777,"CPezzi_D": 832.4,"CQuota": 41.23,"CPrezzo": 12.8},
{"DscProd": "ESTECLIN20CPS 300MG","DscDitta": "EDMOND PHARMA Srl","FFt": 2,"FPz": 2,"FFatt": 11.6,"FFatt_D": null,"FPezzi": 1,"FPezzi_D": null,"FQuota": 50,"FPrezzo": 11.6,"CFt": 1,"CPz": 1,"CFatt": 12.84,"CFatt_D": null,"CPezzi": 1,"CPezzi_D": null,"CQuota": 58.77,"CPrezzo": 11.6},
{"DscProd": "Altre 2 referenze","DscDitta": "1 ditte coinvolte","FFt": 3,"FPz": 3,"FFatt": 0,"FFatt_D": null,"FPezzi": 0,"FPezzi_D": null,"FQuota": 0,"FPrezzo": 0,"CFt": 3,"CPz": 3,"CFatt": 0,"CFatt_D": null,"CPezzi": 0,"CPezzi_D": null,"CQuota": 0,"CPrezzo": 0} 
]}
